arauco/__init__.py
arauco-1.2.dist-info/LICENSE
arauco-1.2.dist-info/METADATA
arauco-1.2.dist-info/WHEEL
arauco-1.2.dist-info/top_level.txt
arauco-1.2.dist-info/RECORD
