Metadata-Version: 2.1
Name: arauco
Version: 1.2
Summary: Simple and useful functions for data analysis
Home-page: https://github.com/ptoledor/pypi-arauco
Author: Pedro Toledo
Author-email: ptoledor@msn.com
License: MIT
Classifier: Programming Language :: Python :: 3
Classifier: License :: OSI Approved :: MIT License
Classifier: Operating System :: OS Independent
Requires-Python: >=3.6
License-File: LICENSE
Requires-Dist: pandas
Requires-Dist: numpy
